ansys/acp/core/__init__.py
ansys/acp/core/_dependency_graph.py
ansys/acp/core/_log.py
ansys/acp/core/_model_printer.py
ansys/acp/core/_plotter.py
ansys/acp/core/_recursive_copy.py
ansys/acp/core/_server/__init__.py
ansys/acp/core/_server/acp_instance.py
ansys/acp/core/_server/common.py
ansys/acp/core/_server/connect.py
ansys/acp/core/_server/direct.py
ansys/acp/core/_server/docker-compose-insecure.yaml
ansys/acp/core/_server/docker-compose-mtls.yaml
ansys/acp/core/_server/docker_compose.py
ansys/acp/core/_server/launch.py
ansys/acp/core/_tree_objects/__init__.py
ansys/acp/core/_tree_objects/_elemental_or_nodal_data.py
ansys/acp/core/_tree_objects/_grpc_helpers/edge_property_list.py
ansys/acp/core/_tree_objects/_grpc_helpers/enum_wrapper.py
ansys/acp/core/_tree_objects/_grpc_helpers/exceptions.py
ansys/acp/core/_tree_objects/_grpc_helpers/linked_object_helpers.py
ansys/acp/core/_tree_objects/_grpc_helpers/linked_object_list.py
ansys/acp/core/_tree_objects/_grpc_helpers/mapping.py
ansys/acp/core/_tree_objects/_grpc_helpers/polymorphic_from_pb.py
ansys/acp/core/_tree_objects/_grpc_helpers/property_helper.py
ansys/acp/core/_tree_objects/_grpc_helpers/protocols.py
ansys/acp/core/_tree_objects/_grpc_helpers/supported_since.py
ansys/acp/core/_tree_objects/_mesh_data.py
ansys/acp/core/_tree_objects/_object_cache.py
ansys/acp/core/_tree_objects/_solid_model_export.py
ansys/acp/core/_tree_objects/analysis_ply.py
ansys/acp/core/_tree_objects/base.py
ansys/acp/core/_tree_objects/boolean_selection_rule.py
ansys/acp/core/_tree_objects/butt_joint_sequence.py
ansys/acp/core/_tree_objects/cad_component.py
ansys/acp/core/_tree_objects/cad_geometry.py
ansys/acp/core/_tree_objects/cut_off_geometry.py
ansys/acp/core/_tree_objects/cut_off_selection_rule.py
ansys/acp/core/_tree_objects/cylindrical_selection_rule.py
ansys/acp/core/_tree_objects/edge_set.py
ansys/acp/core/_tree_objects/element_set.py
ansys/acp/core/_tree_objects/enums.py
ansys/acp/core/_tree_objects/extrusion_guide.py
ansys_acp_core-0.3.1.dist-info/METADATA
ansys_acp_core-0.3.1.dist-info/WHEEL
ansys_acp_core-0.3.1.dist-info/entry_points.txt
ansys_acp_core-0.3.1.dist-info/licenses/AUTHORS
ansys_acp_core-0.3.1.dist-info/licenses/LICENSE
ansys_acp_core-0.3.1.dist-info/RECORD
