Metadata-Version: 2.4
Name: ansys-acp-core
Version: 0.3.1
Summary: Python library for ACP - Ansys Composite PrepPost
License: MIT
License-File: AUTHORS
License-File: LICENSE
Author: ANSYS, Inc.
Author-email: pyansys.core@ansys.com
Maintainer: ANSYS, Inc.
Maintainer-email: pyansys.core@ansys.com
Requires-Python: >=3.10,<3.14
Classifier: Development Status :: 5 - Production/Stable
Classifier: License :: OSI Approved :: MIT License
Classifier: Operating System :: OS Independent
Classifier: Programming Language :: Python :: 3
Classifier: Programming Language :: Python :: 3.10
Classifier: Programming Language :: Python :: 3.11
Classifier: Programming Language :: Python :: 3.12
Classifier: Programming Language :: Python :: 3.13
Classifier: Topic :: Scientific/Engineering
Provides-Extra: all
Provides-Extra: examples
Provides-Extra: graphics
Provides-Extra: plotting
Requires-Dist: ansys-api-acp (==0.3.1)
Requires-Dist: ansys-dpf-composites (>=0.6) ; extra == "examples" or extra == "all"
Requires-Dist: ansys-dpf-core (>=0.13) ; extra == "all"
Requires-Dist: ansys-mapdl-core[graphics] (>=0.68.3) ; extra == "examples" or extra == "all"
Requires-Dist: ansys-mechanical-core (>=0.10.0) ; extra == "examples" or extra == "all"
Requires-Dist: ansys-tools-common (>=0.4.0)
Requires-Dist: ansys-tools-filetransfer (>=0.2.1)
Requires-Dist: grpcio-health-checking (>=1.43)
Requires-Dist: matplotlib (>=3.8.3) ; extra == "examples" or extra == "all"
Requires-Dist: networkx (>=3.0.0)
Requires-Dist: numpy (>=1.22)
Requires-Dist: packaging (>=15.0)
Requires-Dist: pyvista[jupyter] (>=0.42.0,!=0.42.2) ; extra == "plotting" or extra == "graphics" or extra == "all"
Requires-Dist: scipy (>=1.12.0) ; extra == "examples" or extra == "all"
Requires-Dist: typing-extensions (>=4.5.0)
Project-URL: Documentation, https://acp.docs.pyansys.com
Project-URL: Homepage, https://acp.docs.pyansys.com
Project-URL: Issues, https://github.com/ansys/pyacp/issues
Project-URL: Repository, https://github.com/ansys/pyacp/
Project-URL: Releases, https://github.com/ansys/pyacp/releases
